{
  "slug": "a4-bower-harris",
  "query": "Bower Harris",
  "args": {
    "slug": "a4-bower-harris",
    "surname": "Bower Harris",
    "headed": "false",
    "hold": "0"
  },
  "finalUrl": "https://collections.arolsen-archives.org/en/search?s=Bower%20Harris",
  "countMatches": [
    "16"
  ],
  "apiSummary": {
    "personHits": 0,
    "archiveHits": 0,
    "persons": [
      {
        "__type": "ITSPannel.classes.PersData",
        "ObjId": 70203856,
        "LastName": "BAUER",
        "FirstName": "Harry",
        "MaidenName": "",
        "PlaceBirth": "",
        "Dob": "10/16/1937",
        "Year": null,
        "MoreDob": false,
        "PrisonerNumber": "",
        "AUCode": null,
        "DescId": "560069",
        "Counter": 0,
        "TreePath": null,
        "Signature": "2.1.1.1 - Information on foreigners being locally registered (after the war) in the district Rosenheim",
        "Father": "",
        "Mother": "",
        "Religion": "",
        "Nationality": "",
        "Occupaton": "",
        "Place_of_incarceration": "",
        "Date_of_decease": "",
        "Last_residence": "",
        "Last_residence_country": "",
        "Last_residence_district": "",
        "Last_residence_province": "",
        "Last_residence_town": "",
        "Last_residence_part_of_town": "",
        "Last_residence_street": "",
        "Last_residence_house_number": ""
      },
      {
        "__type": "ITSPannel.classes.PersData",
        "ObjId": 70203962,
        "LastName": "BAUER",
        "FirstName": "Harry",
        "MaidenName": "",
        "PlaceBirth": "",
        "Dob": "10/16/1937",
        "Year": null,
        "MoreDob": false,
        "PrisonerNumber": "",
        "AUCode": null,
        "DescId": "560083",
        "Counter": 1,
        "TreePath": null,
        "Signature": "2.1.1.1 - Information of judical and official files of the district Rosenheim concerning foreigners",
        "Father": "",
        "Mother": "",
        "Religion": "",
        "Nationality": "",
        "Occupaton": "",
        "Place_of_incarceration": "",
        "Date_of_decease": "",
        "Last_residence": "",
        "Last_residence_country": "",
        "Last_residence_district": "",
        "Last_residence_province": "",
        "Last_residence_town": "",
        "Last_residence_part_of_town": "",
        "Last_residence_street": "",
        "Last_residence_house_number": ""
      },
      {
        "__type": "ITSPannel.classes.PersData",
        "ObjId": 70752146,
        "LastName": "BAUER",
        "FirstName": "Harry",
        "MaidenName": "",
        "PlaceBirth": "",
        "Dob": "",
        "Year": null,
        "MoreDob": false,
        "PrisonerNumber": "",
        "AUCode": null,
        "DescId": "629466",
        "Counter": 2,
        "TreePath": null,
        "Signature": "2.1.2.1 - Nationality/origin of person listed : Czechoslovakian",
        "Father": "",
        "Mother": "",
        "Religion": "",
        "Nationality": "",
        "Occupaton": "",
        "Place_of_incarceration": "",
        "Date_of_decease": "",
        "Last_residence": "",
        "Last_residence_country": "",
        "Last_residence_district": "",
        "Last_residence_province": "",
        "Last_residence_town": "",
        "Last_residence_part_of_town": "",
        "Last_residence_street": "",
        "Last_residence_house_number": ""
      },
      {
        "__type": "ITSPannel.classes.PersData",
        "ObjId": 70752959,
        "LastName": "BAUER",
        "FirstName": "Harry",
        "MaidenName": "",
        "PlaceBirth": "",
        "Dob": "",
        "Year": null,
        "MoreDob": false,
        "PrisonerNumber": "",
        "AUCode": null,
        "DescId": "629582",
        "Counter": 3,
        "TreePath": null,
        "Signature": "2.1.2.1 - Nationality/origin of person listed : Czechoslovakian",
        "Father": "",
        "Mother": "",
        "Religion": "",
        "Nationality": "",
        "Occupaton": "",
        "Place_of_incarceration": "",
        "Date_of_decease": "",
        "Last_residence": "",
        "Last_residence_country": "",
        "Last_residence_district": "",
        "Last_residence_province": "",
        "Last_residence_town": "",
        "Last_residence_part_of_town": "",
        "Last_residence_street": "",
        "Last_residence_house_number": ""
      },
      {
        "__type": "ITSPannel.classes.PersData",
        "ObjId": 78632306,
        "LastName": "BAUER",
        "FirstName": "Harry Helmut",
        "MaidenName": "",
        "PlaceBirth": "Litzmannstadt",
        "Dob": "12/19/1919",
        "Year": null,
        "MoreDob": false,
        "PrisonerNumber": "",
        "AUCode": null,
        "DescId": "7242",
        "Counter": 4,
        "TreePath": null,
        "Signature": "1.2.2.1 - DANZIG-WESTRPEUSSEN (Reichsgau)",
        "Father": "",
        "Mother": "",
        "Religion": "",
        "Nationality": "",
        "Occupaton": "",
        "Place_of_incarceration": "",
        "Date_of_decease": "",
        "Last_residence": "",
        "Last_residence_country": "",
        "Last_residence_district": "",
        "Last_residence_province": "",
        "Last_residence_town": "",
        "Last_residence_part_of_town": "",
        "Last_residence_street": "",
        "Last_residence_house_number": ""
      },
      {
        "__type": "ITSPannel.classes.PersData",
        "ObjId": 78632310,
        "LastName": "BAUER",
        "FirstName": "Harry Helmut",
        "MaidenName": "",
        "PlaceBirth": "Litzmannstadt",
        "Dob": "12/19/1919",
        "Year": null,
        "MoreDob": false,
        "PrisonerNumber": "",
        "AUCode": null,
        "DescId": "7242",
        "Counter": 5,
        "TreePath": null,
        "Signature": "1.2.2.1 - DANZIG-WESTRPEUSSEN (Reichsgau)",
        "Father": "",
        "Mother": "",
        "Religion": "",
        "Nationality": "",
        "Occupaton": "",
        "Place_of_incarceration": "",
        "Date_of_decease": "",
        "Last_residence": "",
        "Last_residence_country": "",
        "Last_residence_district": "",
        "Last_residence_province": "",
        "Last_residence_town": "",
        "Last_residence_part_of_town": "",
        "Last_residence_street": "",
        "Last_residence_house_number": ""
      },
      {
        "__type": "ITSPannel.classes.PersData",
        "ObjId": 78914065,
        "LastName": "BAUER",
        "FirstName": "HARRY",
        "MaidenName": "",
        "PlaceBirth": "Odessa",
        "Dob": "08/22/1938",
        "Year": null,
        "MoreDob": false,
        "PrisonerNumber": "",
        "AUCode": null,
        "DescId": "2823590",
        "Counter": 6,
        "TreePath": null,
        "Signature": "3.2.1.1 - Files with names from BATIUK",
        "Father": "",
        "Mother": "",
        "Religion": "",
        "Nationality": "",
        "Occupaton": "",
        "Place_of_incarceration": "",
        "Date_of_decease": "",
        "Last_residence": "",
        "Last_residence_country": "",
        "Last_residence_district": "",
        "Last_residence_province": "",
        "Last_residence_town": "",
        "Last_residence_part_of_town": "",
        "Last_residence_street": "",
        "Last_residence_house_number": ""
      },
      {
        "__type": "ITSPannel.classes.PersData",
        "ObjId": 81683070,
        "LastName": "BAUER",
        "FirstName": "Harry",
        "MaidenName": "",
        "PlaceBirth": "",
        "Dob": "",
        "Year": null,
        "MoreDob": false,
        "PrisonerNumber": "",
        "AUCode": null,
        "DescId": "22578",
        "Counter": 7,
        "TreePath": null,
        "Signature": "3.1.3.2 - Emigrations in 1951",
        "Father": "",
        "Mother": "",
        "Religion": "",
        "Nationality": "",
        "Occupaton": "",
        "Place_of_incarceration": "",
        "Date_of_decease": "",
        "Last_residence": "",
        "Last_residence_country": "",
        "Last_residence_district": "",
        "Last_residence_province": "",
        "Last_residence_town": "",
        "Last_residence_part_of_town": "",
        "Last_residence_street": "",
        "Last_residence_house_number": ""
      },
      {
        "__type": "ITSPannel.classes.PersData",
        "ObjId": 81691910,
        "LastName": "BAUER",
        "FirstName": "Harri",
        "MaidenName": "",
        "PlaceBirth": "",
        "Dob": "03/12/1924",
        "Year": null,
        "MoreDob": false,
        "PrisonerNumber": "",
        "AUCode": null,
        "DescId": "22834",
        "Counter": 8,
        "TreePath": null,
        "Signature": "3.1.3.2 - Emigrations in 1954",
        "Father": "",
        "Mother": "",
        "Religion": "",
        "Nationality": "",
        "Occupaton": "",
        "Place_of_incarceration": "",
        "Date_of_decease": "",
        "Last_residence": "",
        "Last_residence_country": "",
        "Last_residence_district": "",
        "Last_residence_province": "",
        "Last_residence_town": "",
        "Last_residence_part_of_town": "",
        "Last_residence_street": "",
        "Last_residence_house_number": ""
      },
      {
        "__type": "ITSPannel.classes.PersData",
        "ObjId": 81794270,
        "LastName": "BAUER",
        "FirstName": "Harry",
        "MaidenName": "",
        "PlaceBirth": "",
        "Dob": "08/22/1938",
        "Year": null,
        "MoreDob": false,
        "PrisonerNumber": "",
        "AUCode": null,
        "DescId": "21616",
        "Counter": 9,
        "TreePath": null,
        "Signature": "3.1.3.2 - Period 1946 - 1952 (chiefly IRO support)",
        "Father": "",
        "Mother": "",
        "Religion": "",
        "Nationality": "",
        "Occupaton": "",
        "Place_of_incarceration": "",
        "Date_of_decease": "",
        "Last_residence": "",
        "Last_residence_country": "",
        "Last_residence_district": "",
        "Last_residence_province": "",
        "Last_residence_town": "",
        "Last_residence_part_of_town": "",
        "Last_residence_street": "",
        "Last_residence_house_number": ""
      },
      {
        "__type": "ITSPannel.classes.PersData",
        "ObjId": 85999687,
        "LastName": "BAUER",
        "FirstName": "HARRY HEINZ",
        "MaidenName": "",
        "PlaceBirth": "",
        "Dob": "09/23/1923",
        "Year": null,
        "MoreDob": false,
        "PrisonerNumber": "",
        "AUCode": null,
        "DescId": "0",
        "Counter": 10,
        "TreePath": null,
        "Signature": "6.3.1.1",
        "Father": "",
        "Mother": "",
        "Religion": "",
        "Nationality": "",
        "Occupaton": "",
        "Place_of_incarceration": "",
        "Date_of_decease": "",
        "Last_residence": "",
        "Last_residence_country": "",
        "Last_residence_district": "",
        "Last_residence_province": "",
        "Last_residence_town": "",
        "Last_residence_part_of_town": "",
        "Last_residence_street": "",
        "Last_residence_house_number": ""
      },
      {
        "__type": "ITSPannel.classes.PersData",
        "ObjId": 70401605,
        "LastName": "BOER",
        "FirstName": "Harry",
        "MaidenName": "",
        "PlaceBirth": "",
        "Dob": "07/17/1923",
        "Year": null,
        "MoreDob": false,
        "PrisonerNumber": "",
        "AUCode": null,
        "DescId": "581230",
        "Counter": 11,
        "TreePath": null,
        "Signature": "2.1.1.1 - Information on foreigners from medical and health authorities of the district Hersfeld",
        "Father": "",
        "Mother": "",
        "Religion": "",
        "Nationality": "",
        "Occupaton": "",
        "Place_of_incarceration": "",
        "Date_of_decease": "",
        "Last_residence": "",
        "Last_residence_country": "",
        "Last_residence_district": "",
        "Last_residence_province": "",
        "Last_residence_town": "",
        "Last_residence_part_of_town": "",
        "Last_residence_street": "",
        "Last_residence_house_number": ""
      },
      {
        "__type": "ITSPannel.classes.PersData",
        "ObjId": 71187298,
        "LastName": "BOWER",
        "FirstName": "Harry Georg",
        "MaidenName": "",
        "PlaceBirth": "",
        "Dob": "10/10/1922",
        "Year": null,
        "MoreDob": false,
        "PrisonerNumber": "",
        "AUCode": null,
        "DescId": "2714447",
        "Counter": 12,
        "TreePath": null,
        "Signature": "2.1.7.5 - Lists of forced laborers and civilians interned by German administration in various other countries",
        "Father": "",
        "Mother": "",
        "Religion": "",
        "Nationality": "",
        "Occupaton": "",
        "Place_of_incarceration": "",
        "Date_of_decease": "",
        "Last_residence": "",
        "Last_residence_country": "",
        "Last_residence_district": "",
        "Last_residence_province": "",
        "Last_residence_town": "",
        "Last_residence_part_of_town": "",
        "Last_residence_street": "",
        "Last_residence_house_number": ""
      },
      {
        "__type": "ITSPannel.classes.PersData",
        "ObjId": 12100413,
        "LastName": "BOYER",
        "FirstName": "HARRY",
        "MaidenName": "",
        "PlaceBirth": "",
        "Dob": "12/22/1914",
        "Year": null,
        "MoreDob": false,
        "PrisonerNumber": "",
        "AUCode": null,
        "DescId": "5429969",
        "Counter": 13,
        "TreePath": null,
        "Signature": "1.2.2.1 - Compilations of names pertaining to documents received by and sent by the headquarters of the criminal investigations police in Berlin",
        "Father": "",
        "Mother": "",
        "Religion": "",
        "Nationality": "",
        "Occupaton": "",
        "Place_of_incarceration": "",
        "Date_of_decease": "",
        "Last_residence": "",
        "Last_residence_country": "",
        "Last_residence_district": "",
        "Last_residence_province": "",
        "Last_residence_town": "",
        "Last_residence_part_of_town": "",
        "Last_residence_street": "",
        "Last_residence_house_number": ""
      },
      {
        "__type": "ITSPannel.classes.PersData",
        "ObjId": 70397576,
        "LastName": "BOYER",
        "FirstName": "Harry",
        "MaidenName": "",
        "PlaceBirth": "",
        "Dob": "",
        "Year": null,
        "MoreDob": false,
        "PrisonerNumber": "",
        "AUCode": null,
        "DescId": "580332",
        "Counter": 14,
        "TreePath": null,
        "Signature": "2.1.1.1 - Information on foreigners being permanantly or temporarily present in the district Hanau during the war",
        "Father": "",
        "Mother": "",
        "Religion": "",
        "Nationality": "",
        "Occupaton": "",
        "Place_of_incarceration": "",
        "Date_of_decease": "",
        "Last_residence": "",
        "Last_residence_country": "",
        "Last_residence_district": "",
        "Last_residence_province": "",
        "Last_residence_town": "",
        "Last_residence_part_of_town": "",
        "Last_residence_street": "",
        "Last_residence_house_number": ""
      },
      {
        "__type": "ITSPannel.classes.PersData",
        "ObjId": 81689853,
        "LastName": "BOYER",
        "FirstName": "Harry",
        "MaidenName": "",
        "PlaceBirth": "",
        "Dob": "02/01/1930",
        "Year": null,
        "MoreDob": false,
        "PrisonerNumber": "",
        "AUCode": null,
        "DescId": "22766",
        "Counter": 15,
        "TreePath": null,
        "Signature": "3.1.3.2 - Emigrations in 1952/1953",
        "Father": "",
        "Mother": "",
        "Religion": "",
        "Nationality": "",
        "Occupaton": "",
        "Place_of_incarceration": "",
        "Date_of_decease": "",
        "Last_residence": "",
        "Last_residence_country": "",
        "Last_residence_district": "",
        "Last_residence_province": "",
        "Last_residence_town": "",
        "Last_residence_part_of_town": "",
        "Last_residence_street": "",
        "Last_residence_house_number": ""
      }
    ],
    "archives": [],
    "counts": [
      {
        "url": "https://collections-server.arolsen-archives.org/ITS-WS.asmx/GetCount",
        "value": 16,
        "postData": "{\"uniqueId\":\"UmsdbMY4GsItJ7x1JzbE\",\"lang\":\"en\",\"searchType\":\"person\",\"useFilter\":false}"
      },
      {
        "url": "https://collections-server.arolsen-archives.org/ITS-WS.asmx/GetCount",
        "value": 0,
        "postData": "{\"uniqueId\":\"UmsdbMY4GsItJ7x1JzbE\",\"lang\":\"en\",\"searchType\":\"archive\",\"useFilter\":false}"
      },
      {
        "url": "https://collections-server.arolsen-archives.org/ITS-WS.asmx/GetCount",
        "value": 0,
        "postData": "{\"uniqueId\":\"UmsdbMY4GsItJ7x1JzbE\",\"lang\":\"en\",\"searchType\":\"person\",\"useFilter\":true}"
      }
    ]
  },
  "filtered": {
    "persons": [
      {
        "__type": "ITSPannel.classes.PersData",
        "ObjId": 70203856,
        "LastName": "BAUER",
        "FirstName": "Harry",
        "MaidenName": "",
        "PlaceBirth": "",
        "Dob": "10/16/1937",
        "Year": null,
        "MoreDob": false,
        "PrisonerNumber": "",
        "AUCode": null,
        "DescId": "560069",
        "Counter": 0,
        "TreePath": null,
        "Signature": "2.1.1.1 - Information on foreigners being locally registered (after the war) in the district Rosenheim",
        "Father": "",
        "Mother": "",
        "Religion": "",
        "Nationality": "",
        "Occupaton": "",
        "Place_of_incarceration": "",
        "Date_of_decease": "",
        "Last_residence": "",
        "Last_residence_country": "",
        "Last_residence_district": "",
        "Last_residence_province": "",
        "Last_residence_town": "",
        "Last_residence_part_of_town": "",
        "Last_residence_street": "",
        "Last_residence_house_number": ""
      },
      {
        "__type": "ITSPannel.classes.PersData",
        "ObjId": 70203962,
        "LastName": "BAUER",
        "FirstName": "Harry",
        "MaidenName": "",
        "PlaceBirth": "",
        "Dob": "10/16/1937",
        "Year": null,
        "MoreDob": false,
        "PrisonerNumber": "",
        "AUCode": null,
        "DescId": "560083",
        "Counter": 1,
        "TreePath": null,
        "Signature": "2.1.1.1 - Information of judical and official files of the district Rosenheim concerning foreigners",
        "Father": "",
        "Mother": "",
        "Religion": "",
        "Nationality": "",
        "Occupaton": "",
        "Place_of_incarceration": "",
        "Date_of_decease": "",
        "Last_residence": "",
        "Last_residence_country": "",
        "Last_residence_district": "",
        "Last_residence_province": "",
        "Last_residence_town": "",
        "Last_residence_part_of_town": "",
        "Last_residence_street": "",
        "Last_residence_house_number": ""
      },
      {
        "__type": "ITSPannel.classes.PersData",
        "ObjId": 70752146,
        "LastName": "BAUER",
        "FirstName": "Harry",
        "MaidenName": "",
        "PlaceBirth": "",
        "Dob": "",
        "Year": null,
        "MoreDob": false,
        "PrisonerNumber": "",
        "AUCode": null,
        "DescId": "629466",
        "Counter": 2,
        "TreePath": null,
        "Signature": "2.1.2.1 - Nationality/origin of person listed : Czechoslovakian",
        "Father": "",
        "Mother": "",
        "Religion": "",
        "Nationality": "",
        "Occupaton": "",
        "Place_of_incarceration": "",
        "Date_of_decease": "",
        "Last_residence": "",
        "Last_residence_country": "",
        "Last_residence_district": "",
        "Last_residence_province": "",
        "Last_residence_town": "",
        "Last_residence_part_of_town": "",
        "Last_residence_street": "",
        "Last_residence_house_number": ""
      },
      {
        "__type": "ITSPannel.classes.PersData",
        "ObjId": 70752959,
        "LastName": "BAUER",
        "FirstName": "Harry",
        "MaidenName": "",
        "PlaceBirth": "",
        "Dob": "",
        "Year": null,
        "MoreDob": false,
        "PrisonerNumber": "",
        "AUCode": null,
        "DescId": "629582",
        "Counter": 3,
        "TreePath": null,
        "Signature": "2.1.2.1 - Nationality/origin of person listed : Czechoslovakian",
        "Father": "",
        "Mother": "",
        "Religion": "",
        "Nationality": "",
        "Occupaton": "",
        "Place_of_incarceration": "",
        "Date_of_decease": "",
        "Last_residence": "",
        "Last_residence_country": "",
        "Last_residence_district": "",
        "Last_residence_province": "",
        "Last_residence_town": "",
        "Last_residence_part_of_town": "",
        "Last_residence_street": "",
        "Last_residence_house_number": ""
      },
      {
        "__type": "ITSPannel.classes.PersData",
        "ObjId": 78632306,
        "LastName": "BAUER",
        "FirstName": "Harry Helmut",
        "MaidenName": "",
        "PlaceBirth": "Litzmannstadt",
        "Dob": "12/19/1919",
        "Year": null,
        "MoreDob": false,
        "PrisonerNumber": "",
        "AUCode": null,
        "DescId": "7242",
        "Counter": 4,
        "TreePath": null,
        "Signature": "1.2.2.1 - DANZIG-WESTRPEUSSEN (Reichsgau)",
        "Father": "",
        "Mother": "",
        "Religion": "",
        "Nationality": "",
        "Occupaton": "",
        "Place_of_incarceration": "",
        "Date_of_decease": "",
        "Last_residence": "",
        "Last_residence_country": "",
        "Last_residence_district": "",
        "Last_residence_province": "",
        "Last_residence_town": "",
        "Last_residence_part_of_town": "",
        "Last_residence_street": "",
        "Last_residence_house_number": ""
      },
      {
        "__type": "ITSPannel.classes.PersData",
        "ObjId": 78632310,
        "LastName": "BAUER",
        "FirstName": "Harry Helmut",
        "MaidenName": "",
        "PlaceBirth": "Litzmannstadt",
        "Dob": "12/19/1919",
        "Year": null,
        "MoreDob": false,
        "PrisonerNumber": "",
        "AUCode": null,
        "DescId": "7242",
        "Counter": 5,
        "TreePath": null,
        "Signature": "1.2.2.1 - DANZIG-WESTRPEUSSEN (Reichsgau)",
        "Father": "",
        "Mother": "",
        "Religion": "",
        "Nationality": "",
        "Occupaton": "",
        "Place_of_incarceration": "",
        "Date_of_decease": "",
        "Last_residence": "",
        "Last_residence_country": "",
        "Last_residence_district": "",
        "Last_residence_province": "",
        "Last_residence_town": "",
        "Last_residence_part_of_town": "",
        "Last_residence_street": "",
        "Last_residence_house_number": ""
      },
      {
        "__type": "ITSPannel.classes.PersData",
        "ObjId": 78914065,
        "LastName": "BAUER",
        "FirstName": "HARRY",
        "MaidenName": "",
        "PlaceBirth": "Odessa",
        "Dob": "08/22/1938",
        "Year": null,
        "MoreDob": false,
        "PrisonerNumber": "",
        "AUCode": null,
        "DescId": "2823590",
        "Counter": 6,
        "TreePath": null,
        "Signature": "3.2.1.1 - Files with names from BATIUK",
        "Father": "",
        "Mother": "",
        "Religion": "",
        "Nationality": "",
        "Occupaton": "",
        "Place_of_incarceration": "",
        "Date_of_decease": "",
        "Last_residence": "",
        "Last_residence_country": "",
        "Last_residence_district": "",
        "Last_residence_province": "",
        "Last_residence_town": "",
        "Last_residence_part_of_town": "",
        "Last_residence_street": "",
        "Last_residence_house_number": ""
      },
      {
        "__type": "ITSPannel.classes.PersData",
        "ObjId": 81683070,
        "LastName": "BAUER",
        "FirstName": "Harry",
        "MaidenName": "",
        "PlaceBirth": "",
        "Dob": "",
        "Year": null,
        "MoreDob": false,
        "PrisonerNumber": "",
        "AUCode": null,
        "DescId": "22578",
        "Counter": 7,
        "TreePath": null,
        "Signature": "3.1.3.2 - Emigrations in 1951",
        "Father": "",
        "Mother": "",
        "Religion": "",
        "Nationality": "",
        "Occupaton": "",
        "Place_of_incarceration": "",
        "Date_of_decease": "",
        "Last_residence": "",
        "Last_residence_country": "",
        "Last_residence_district": "",
        "Last_residence_province": "",
        "Last_residence_town": "",
        "Last_residence_part_of_town": "",
        "Last_residence_street": "",
        "Last_residence_house_number": ""
      },
      {
        "__type": "ITSPannel.classes.PersData",
        "ObjId": 81691910,
        "LastName": "BAUER",
        "FirstName": "Harri",
        "MaidenName": "",
        "PlaceBirth": "",
        "Dob": "03/12/1924",
        "Year": null,
        "MoreDob": false,
        "PrisonerNumber": "",
        "AUCode": null,
        "DescId": "22834",
        "Counter": 8,
        "TreePath": null,
        "Signature": "3.1.3.2 - Emigrations in 1954",
        "Father": "",
        "Mother": "",
        "Religion": "",
        "Nationality": "",
        "Occupaton": "",
        "Place_of_incarceration": "",
        "Date_of_decease": "",
        "Last_residence": "",
        "Last_residence_country": "",
        "Last_residence_district": "",
        "Last_residence_province": "",
        "Last_residence_town": "",
        "Last_residence_part_of_town": "",
        "Last_residence_street": "",
        "Last_residence_house_number": ""
      },
      {
        "__type": "ITSPannel.classes.PersData",
        "ObjId": 81794270,
        "LastName": "BAUER",
        "FirstName": "Harry",
        "MaidenName": "",
        "PlaceBirth": "",
        "Dob": "08/22/1938",
        "Year": null,
        "MoreDob": false,
        "PrisonerNumber": "",
        "AUCode": null,
        "DescId": "21616",
        "Counter": 9,
        "TreePath": null,
        "Signature": "3.1.3.2 - Period 1946 - 1952 (chiefly IRO support)",
        "Father": "",
        "Mother": "",
        "Religion": "",
        "Nationality": "",
        "Occupaton": "",
        "Place_of_incarceration": "",
        "Date_of_decease": "",
        "Last_residence": "",
        "Last_residence_country": "",
        "Last_residence_district": "",
        "Last_residence_province": "",
        "Last_residence_town": "",
        "Last_residence_part_of_town": "",
        "Last_residence_street": "",
        "Last_residence_house_number": ""
      },
      {
        "__type": "ITSPannel.classes.PersData",
        "ObjId": 85999687,
        "LastName": "BAUER",
        "FirstName": "HARRY HEINZ",
        "MaidenName": "",
        "PlaceBirth": "",
        "Dob": "09/23/1923",
        "Year": null,
        "MoreDob": false,
        "PrisonerNumber": "",
        "AUCode": null,
        "DescId": "0",
        "Counter": 10,
        "TreePath": null,
        "Signature": "6.3.1.1",
        "Father": "",
        "Mother": "",
        "Religion": "",
        "Nationality": "",
        "Occupaton": "",
        "Place_of_incarceration": "",
        "Date_of_decease": "",
        "Last_residence": "",
        "Last_residence_country": "",
        "Last_residence_district": "",
        "Last_residence_province": "",
        "Last_residence_town": "",
        "Last_residence_part_of_town": "",
        "Last_residence_street": "",
        "Last_residence_house_number": ""
      },
      {
        "__type": "ITSPannel.classes.PersData",
        "ObjId": 70401605,
        "LastName": "BOER",
        "FirstName": "Harry",
        "MaidenName": "",
        "PlaceBirth": "",
        "Dob": "07/17/1923",
        "Year": null,
        "MoreDob": false,
        "PrisonerNumber": "",
        "AUCode": null,
        "DescId": "581230",
        "Counter": 11,
        "TreePath": null,
        "Signature": "2.1.1.1 - Information on foreigners from medical and health authorities of the district Hersfeld",
        "Father": "",
        "Mother": "",
        "Religion": "",
        "Nationality": "",
        "Occupaton": "",
        "Place_of_incarceration": "",
        "Date_of_decease": "",
        "Last_residence": "",
        "Last_residence_country": "",
        "Last_residence_district": "",
        "Last_residence_province": "",
        "Last_residence_town": "",
        "Last_residence_part_of_town": "",
        "Last_residence_street": "",
        "Last_residence_house_number": ""
      },
      {
        "__type": "ITSPannel.classes.PersData",
        "ObjId": 71187298,
        "LastName": "BOWER",
        "FirstName": "Harry Georg",
        "MaidenName": "",
        "PlaceBirth": "",
        "Dob": "10/10/1922",
        "Year": null,
        "MoreDob": false,
        "PrisonerNumber": "",
        "AUCode": null,
        "DescId": "2714447",
        "Counter": 12,
        "TreePath": null,
        "Signature": "2.1.7.5 - Lists of forced laborers and civilians interned by German administration in various other countries",
        "Father": "",
        "Mother": "",
        "Religion": "",
        "Nationality": "",
        "Occupaton": "",
        "Place_of_incarceration": "",
        "Date_of_decease": "",
        "Last_residence": "",
        "Last_residence_country": "",
        "Last_residence_district": "",
        "Last_residence_province": "",
        "Last_residence_town": "",
        "Last_residence_part_of_town": "",
        "Last_residence_street": "",
        "Last_residence_house_number": ""
      },
      {
        "__type": "ITSPannel.classes.PersData",
        "ObjId": 12100413,
        "LastName": "BOYER",
        "FirstName": "HARRY",
        "MaidenName": "",
        "PlaceBirth": "",
        "Dob": "12/22/1914",
        "Year": null,
        "MoreDob": false,
        "PrisonerNumber": "",
        "AUCode": null,
        "DescId": "5429969",
        "Counter": 13,
        "TreePath": null,
        "Signature": "1.2.2.1 - Compilations of names pertaining to documents received by and sent by the headquarters of the criminal investigations police in Berlin",
        "Father": "",
        "Mother": "",
        "Religion": "",
        "Nationality": "",
        "Occupaton": "",
        "Place_of_incarceration": "",
        "Date_of_decease": "",
        "Last_residence": "",
        "Last_residence_country": "",
        "Last_residence_district": "",
        "Last_residence_province": "",
        "Last_residence_town": "",
        "Last_residence_part_of_town": "",
        "Last_residence_street": "",
        "Last_residence_house_number": ""
      },
      {
        "__type": "ITSPannel.classes.PersData",
        "ObjId": 70397576,
        "LastName": "BOYER",
        "FirstName": "Harry",
        "MaidenName": "",
        "PlaceBirth": "",
        "Dob": "",
        "Year": null,
        "MoreDob": false,
        "PrisonerNumber": "",
        "AUCode": null,
        "DescId": "580332",
        "Counter": 14,
        "TreePath": null,
        "Signature": "2.1.1.1 - Information on foreigners being permanantly or temporarily present in the district Hanau during the war",
        "Father": "",
        "Mother": "",
        "Religion": "",
        "Nationality": "",
        "Occupaton": "",
        "Place_of_incarceration": "",
        "Date_of_decease": "",
        "Last_residence": "",
        "Last_residence_country": "",
        "Last_residence_district": "",
        "Last_residence_province": "",
        "Last_residence_town": "",
        "Last_residence_part_of_town": "",
        "Last_residence_street": "",
        "Last_residence_house_number": ""
      },
      {
        "__type": "ITSPannel.classes.PersData",
        "ObjId": 81689853,
        "LastName": "BOYER",
        "FirstName": "Harry",
        "MaidenName": "",
        "PlaceBirth": "",
        "Dob": "02/01/1930",
        "Year": null,
        "MoreDob": false,
        "PrisonerNumber": "",
        "AUCode": null,
        "DescId": "22766",
        "Counter": 15,
        "TreePath": null,
        "Signature": "3.1.3.2 - Emigrations in 1952/1953",
        "Father": "",
        "Mother": "",
        "Religion": "",
        "Nationality": "",
        "Occupaton": "",
        "Place_of_incarceration": "",
        "Date_of_decease": "",
        "Last_residence": "",
        "Last_residence_country": "",
        "Last_residence_district": "",
        "Last_residence_province": "",
        "Last_residence_town": "",
        "Last_residence_part_of_town": "",
        "Last_residence_street": "",
        "Last_residence_house_number": ""
      }
    ],
    "archives": []
  },
  "domRows": [
    [
      "Signature",
      "Last Name",
      "First Name",
      "Maiden Name",
      "Place of Birth",
      "Date of Birth",
      "Prisoner #",
      "Father (adoptive father)",
      "Mother (adoptive mother)",
      "Religion",
      "Nationality",
      "Occupaton",
      "Place of incarceration",
      "Date of decease",
      "Last residence",
      "Last residence (Country)",
      "Last residence (District)",
      "Last residence (Province)",
      "Last residence (Town)",
      "Last residence (Part of town)",
      "Last residence (Street)",
      "Last residence (House number)"
    ],
    [
      "Signature",
      "Last Name",
      "First Name",
      "Maiden Name",
      "Place of Birth",
      "Date of Birth",
      "Prisoner #"
    ],
    [
      "Signature",
      "Title"
    ],
    [
      "Reference code",
      "Signature",
      "Title",
      "hierarchy list"
    ]
  ],
  "domCards": [
    "Welcome to the Online Archive of the Arolsen Archives! The Arolsen Archives are an international center on Nazi persecution with the world’s most extensive collection of documents about the victims and survivors of National Socialism. The documents relate to the various groups persecuted by the Nazi regime and contain references to around 17.5 million people, making them an important source of knowledge for society today. Many of the around 30 million documents are now available in the Online Archive of the Arolsen Archives. The number of searchable names and keywords is growing all the time. "
  ],
  "links": [
    {
      "text": "Search",
      "href": "https://collections.arolsen-archives.org/en/search"
    },
    {
      "text": "Browse archive",
      "href": "https://collections.arolsen-archives.org/en/archive"
    },
    {
      "text": "Donate",
      "href": "https://arolsen-archives.org/en/about-us/support-us/"
    },
    {
      "text": "Newsletter",
      "href": "https://arolsen-archives.org/en/news-events/newsletter/"
    },
    {
      "text": "Contact",
      "href": "https://arolsen-archives.org/en/contact/"
    },
    {
      "text": "About Us",
      "href": "https://arolsen-archives.org/en/about-us/"
    },
    {
      "text": "",
      "href": "https://collections.arolsen-archives.org/"
    },
    {
      "text": "Search",
      "href": "https://collections.arolsen-archives.org/en/search"
    },
    {
      "text": "Browse archive",
      "href": "https://collections.arolsen-archives.org/en/archive"
    },
    {
      "text": "Detailed questions/information about thedocuments? Send us an inquiry for free.",
      "href": "https://arolsen-archives.org/en/search-explore/inquiries/"
    },
    {
      "text": "Donate",
      "href": "https://arolsen-archives.org/en/about-us/support-us/"
    },
    {
      "text": "Newsletter",
      "href": "https://arolsen-archives.org/en/news-events/newsletter/"
    },
    {
      "text": "Contact",
      "href": "https://arolsen-archives.org/en/contact/"
    },
    {
      "text": "About Us",
      "href": "https://arolsen-archives.org/en/about-us/"
    },
    {
      "text": "Open e-Guide",
      "href": "https://eguide.arolsen-archives.org/en/"
    },
    {
      "text": "Send inquiry",
      "href": "https://arolsen-archives.org/en/search-explore/inquiries/"
    },
    {
      "text": "#everynamecounts",
      "href": "https://arolsen-archives.org/en/learn-participate/exhibitions-campaigns/everynamecounts/"
    },
    {
      "text": "Legal notice",
      "href": "https://arolsen-archives.org/en/legal-notice/"
    },
    {
      "text": "Privacy policy",
      "href": "https://arolsen-archives.org/en/privacy-policy/"
    },
    {
      "text": "Imprint",
      "href": "https://arolsen-archives.org/en/legal-notice/"
    },
    {
      "text": "Privacy Policy",
      "href": "https://arolsen-archives.org/en/privacy-policy/"
    }
  ],
  "apiResponses": [
    {
      "url": "https://collections-server.arolsen-archives.org/ITS-WS.asmx/BuildQueryGlobalForAngular",
      "status": 200,
      "requestPostData": "{\"uniqueId\":\"UmsdbMY4GsItJ7x1JzbE\",\"lang\":\"en\",\"archiveIds\":[],\"strSearch\":\"Bower Harris\",\"synSearch\":true}",
      "body": "{\"d\":true}"
    },
    {
      "url": "https://collections-server.arolsen-archives.org/ITS-WS.asmx/GetArchiveList",
      "status": 200,
      "requestPostData": "{\"uniqueId\":\"UmsdbMY4GsItJ7x1JzbE\",\"lang\":\"en\",\"orderBy\":\"RN\",\"orderType\":\"asc\",\"rowNum\":0}",
      "body": "{\"d\":[]}"
    },
    {
      "url": "https://collections-server.arolsen-archives.org/ITS-WS.asmx/GetCount",
      "status": 200,
      "requestPostData": "{\"uniqueId\":\"UmsdbMY4GsItJ7x1JzbE\",\"lang\":\"en\",\"searchType\":\"person\",\"useFilter\":false}",
      "body": "{\"d\":\"16\"}"
    },
    {
      "url": "https://collections-server.arolsen-archives.org/ITS-WS.asmx/GetPersonList",
      "status": 200,
      "requestPostData": "{\"uniqueId\":\"UmsdbMY4GsItJ7x1JzbE\",\"lang\":\"en\",\"rowNum\":0,\"orderBy\":\"LastName\",\"orderType\":\"asc\"}",
      "body": "{\"d\":[{\"__type\":\"ITSPannel.classes.PersData\",\"ObjId\":70203856,\"LastName\":\"BAUER\",\"FirstName\":\"Harry\",\"MaidenName\":\"\",\"PlaceBirth\":\"\",\"Dob\":\"10/16/1937\",\"Year\":null,\"MoreDob\":false,\"PrisonerNumber\":\"\",\"AUCode\":null,\"DescId\":\"560069\",\"Counter\":0,\"TreePath\":null,\"Signature\":\"2.1.1.1 - Information on foreigners being locally registered (after the war) in the district Rosenheim\",\"Father\":\"\",\"Mother\":\"\",\"Religion\":\"\",\"Nationality\":\"\",\"Occupaton\":\"\",\"Place_of_incarceration\":\"\",\"Date_of_decease\":\"\",\"Last_residence\":\"\",\"Last_residence_country\":\"\",\"Last_residence_district\":\"\",\"Last_residence_province\":\"\",\"Last_residence_town\":\"\",\"Last_residence_part_of_town\":\"\",\"Last_residence_street\":\"\",\"Last_residence_house_number\":\"\"},{\"__type\":\"ITSPannel.classes.PersData\",\"ObjId\":70203962,\"LastName\":\"BAUER\",\"FirstName\":\"Harry\",\"MaidenName\":\"\",\"PlaceBirth\":\"\",\"Dob\":\"10/16/1937\",\"Year\":null,\"MoreDob\":false,\"PrisonerNumber\":\"\",\"AUCode\":null,\"DescId\":\"560083\",\"Counter\":1,\"TreePath\":null,\"Signature\":\"2.1.1.1 - Information of judical and official files of the district Rosenheim concerning foreigners\",\"Father\":\"\",\"Mother\":\"\",\"Religion\":\"\",\"Nationality\":\"\",\"Occupaton\":\"\",\"Place_of_incarceration\":\"\",\"Date_of_decease\":\"\",\"Last_residence\":\"\",\"Last_residence_country\":\"\",\"Last_residence_district\":\"\",\"Last_residence_province\":\"\",\"Last_residence_town\":\"\",\"Last_residence_part_of_town\":\"\",\"Last_residence_street\":\"\",\"Last_residence_house_number\":\"\"},{\"__type\":\"ITSPannel.classes.PersData\",\"ObjId\":70752146,\"LastName\":\"BAUER\",\"FirstName\":\"Harry\",\"MaidenName\":\"\",\"PlaceBirth\":\"\",\"Dob\":\"\",\"Year\":null,\"MoreDob\":false,\"PrisonerNumber\":\"\",\"AUCode\":null,\"DescId\":\"629466\",\"Counter\":2,\"TreePath\":null,\"Signature\":\"2.1.2.1 - Nationality/origin of person listed : Czechoslovakian\",\"Father\":\"\",\"Mother\":\"\",\"Religion\":\"\",\"Nationality\":\"\",\"Occupaton\":\"\",\"Place_of_incarceration\":\"\",\"Date_of_decease\":\"\",\"Last_residence\":\"\",\"Last_residence_country\":\"\",\"Last_residence_district\":\"\",\"Last_residence_province\":\"\",\"Last_residence_town\":\"\",\"Last_residence_part_of_town\":\"\",\"Last_residence_street\":\"\",\"Last_residence_house_number\":\"\"},{\"__type\":\"ITSPannel.classes.PersData\",\"ObjId\":70752959,\"LastName\":\"BAUER\",\"FirstName\":\"Harry\",\"MaidenName\":\"\",\"PlaceBirth\":\"\",\"Dob\":\"\",\"Year\":null,\"MoreDob\":false,\"PrisonerNumber\":\"\",\"AUCode\":null,\"DescId\":\"629582\",\"Counter\":3,\"TreePath\":null,\"Signature\":\"2.1.2.1 - Nationality/origin of person listed : Czechoslovakian\",\"Father\":\"\",\"Mother\":\"\",\"Religion\":\"\",\"Nationality\":\"\",\"Occupaton\":\"\",\"Place_of_incarceration\":\"\",\"Date_of_decease\":\"\",\"Last_residence\":\"\",\"Last_residence_country\":\"\",\"Last_residence_district\":\"\",\"Last_residence_province\":\"\",\"Last_residence_town\":\"\",\"Last_residence_part_of_town\":\"\",\"Last_residence_street\":\"\",\"Last_residence_house_number\":\"\"},{\"__type\":\"ITSPannel.classes.PersData\",\"ObjId\":78632306,\"LastName\":\"BAUER\",\"FirstName\":\"Harry Helmut\",\"MaidenName\":\"\",\"PlaceBirth\":\"Litzmannstadt\",\"Dob\":\"12/19/1919\",\"Year\":null,\"MoreDob\":false,\"PrisonerNumber\":\"\",\"AUCode\":null,\"DescId\":\"7242\",\"Counter\":4,\"TreePath\":null,\"Signature\":\"1.2.2.1 - DANZIG-WESTRPEUSSEN (Reichsgau)\",\"Father\":\"\",\"Mother\":\"\",\"Religion\":\"\",\"Nationality\":\"\",\"Occupaton\":\"\",\"Place_of_incarceration\":\"\",\"Date_of_decease\":\"\",\"Last_residence\":\"\",\"Last_residence_country\":\"\",\"Last_residence_district\":\"\",\"Last_residence_province\":\"\",\"Last_residence_town\":\"\",\"Last_residence_part_of_town\":\"\",\"Last_residence_street\":\"\",\"Last_residence_house_number\":\"\"},{\"__type\":\"ITSPannel.classes.PersData\",\"ObjId\":78632310,\"LastName\":\"BAUER\",\"FirstName\":\"Harry Helmut\",\"MaidenName\":\"\",\"PlaceBirth\":\"Litzmannstadt\",\"Dob\":\"12/19/1919\",\"Year\":null,\"MoreDob\":false,\"PrisonerNumber\":\"\",\"AUCode\":null,\"DescId\":\"7242\",\"Counter\":5,\"TreePath\":null,\"Signature\":\"1.2.2.1 - DANZIG-WESTRPEUSSEN (Reichsgau)\",\"Father\":\"\",\"Mother\":\"\",\"Religion\":\"\",\"Nationality\":\"\",\"Occupaton\":\"\",\"Place_of_incarceration\":\"\",\"Date_of_decease\":\"\",\"Last_residence\":\"\",\"Last_residence_country\":\"\",\"Last_residence_district\":\"\",\"Last_residence_province\":\"\",\"Last_residence_town\":\"\",\"Last_residence_part_of_town\":\"\",\"Last_residence_street\":\"\",\"Last_residence_house_number\":\"\"},{\"__type\":\"ITSPannel.classes.PersData\",\"ObjId\":78914065,\"LastName\":\"BAUER\",\"FirstName\":\"HARRY\",\"MaidenName\":\"\",\"PlaceBirth\":\"Odessa\",\"Dob\":\"08/22/1938\",\"Year\":null,\"MoreDob\":false,\"PrisonerNumber\":\"\",\"AUCode\":null,\"DescId\":\"2823590\",\"Counter\":6,\"TreePath\":null,\"Signature\":\"3.2.1.1 - Files with names from BATIUK\",\"Father\":\"\",\"Mother\":\"\",\"Religion\":\"\",\"Nationality\":\"\",\"Occupaton\":\"\",\"Place_of_incarceration\":\"\",\"Date_of_decease\":\"\",\"Last_residence\":\"\",\"Last_residence_country\":\"\",\"Last_residence_district\":\"\",\"Last_residence_province\":\"\",\"Last_residence_town\":\"\",\"Last_residence_part_of_town\":\"\",\"Last_residence_street\":\"\",\"Last_residence_house_number\":\"\"},{\"__type\":\"ITSPannel.classes.PersData\",\"ObjId\":81683070,\"LastName\":\"BAUER\",\"FirstName\":\"Harry\",\"MaidenName\":\"\",\"PlaceBirth\":\"\",\"Dob\":\"\",\"Year\":null,\"MoreDob\":false,\"PrisonerNumber\":\"\",\"AUCode\":null,\"DescId\":\"22578\",\"Counter\":7,\"TreePath\":null,\"Signature\":\"3.1.3.2 - Emigrations in 1951\",\"Father\":\"\",\"Mother\":\"\",\"Religion\":\"\",\"Nationality\":\"\",\"Occupaton\":\"\",\"Place_of_incarceration\":\"\",\"Date_of_decease\":\"\",\"Last_residence\":\"\",\"Last_residence_country\":\"\",\"Last_residence_district\":\"\",\"Last_residence_province\":\"\",\"Last_residence_town\":\"\",\"Last_residence_part_of_town\":\"\",\"Last_residence_street\":\"\",\"Last_residence_house_number\":\"\"},{\"__type\":\"ITSPannel.classes.PersData\",\"ObjId\":81691910,\"LastName\":\"BAUER\",\"FirstName\":\"Harri\",\"MaidenName\":\"\",\"PlaceBirth\":\"\",\"Dob\":\"03/12/1924\",\"Year\":null,\"MoreDob\":false,\"PrisonerNumber\":\"\",\"AUCode\":null,\"DescId\":\"22834\",\"Counter\":8,\"TreePath\":null,\"Signature\":\"3.1.3.2 - Emigrations in 1954\",\"Father\":\"\",\"Mother\":\"\",\"Religion\":\"\",\"Nationality\":\"\",\"Occupaton\":\"\",\"Place_of_incarceration\":\"\",\"Date_of_decease\":\"\",\"Last_residence\":\"\",\"Last_residence_country\":\"\",\"Last_residence_district\":\"\",\"Last_residence_province\":\"\",\"Last_residence_town\":\"\",\"Last_residence_part_of_town\":\"\",\"Last_residence_street\":\"\",\"Last_residence_house_number\":\"\"},{\"__type\":\"ITSPannel.classes.PersData\",\"ObjId\":81794270,\"LastName\":\"BAUER\",\"FirstName\":\"Harry\",\"MaidenName\":\"\",\"PlaceBirth\":\"\",\"Dob\":\"08/22/1938\",\"Year\":null,\"MoreDob\":false,\"PrisonerNumber\":\"\",\"AUCode\":null,\"DescId\":\"21616\",\"Counter\":9,\"TreePath\":null,\"Signature\":\"3.1.3.2 - Period 1946 - 1952 (chiefly IRO support)\",\"Father\":\"\",\"Mother\":\"\",\"Religion\":\"\",\"Nationality\":\"\",\"Occupaton\":\"\",\"Place_of_incarceration\":\"\",\"Date_of_decease\":\"\",\"Last_residence\":\"\",\"Last_residence_country\":\"\",\"Last_residence_district\":\"\",\"Last_residence_province\":\"\",\"Last_residence_town\":\"\",\"Last_residence_part_of_town\":\"\",\"Last_residence_street\":\"\",\"Last_residence_house_number\":\"\"},{\"__type\":\"ITSPannel.classes.PersData\",\"ObjId\":85999687,\"LastName\":\"BAUER\",\"FirstName\":\"HARRY HEINZ\",\"MaidenName\":\"\",\"PlaceBirth\":\"\",\"Dob\":\"09/23/1923\",\"Year\":null,\"MoreDob\":false,\"PrisonerNumber\":\"\",\"AUCode\":null,\"DescId\":\"0\",\"Counter\":10,\"TreePath\":null,\"Signature\":\"6.3.1.1\",\"Father\":\"\",\"Mother\":\"\",\"Religion\":\"\",\"Nationality\":\"\",\"Occupaton\":\"\",\"Place_of_incarceration\":\"\",\"Date_of_decease\":\"\",\"Last_residence\":\"\",\"Last_residence_country\":\"\",\"Last_residence_district\":\"\",\"Last_residence_province\":\"\",\"Last_residence_town\":\"\",\"Last_residence_part_of_town\":\"\",\"Last_residence_street\":\"\",\"Last_residence_house_number\":\"\"},{\"__type\":\"ITSPannel.classes.PersData\",\"ObjId\":70401605,\"LastName\":\"BOER\",\"FirstName\":\"Harry\",\"MaidenName\":\"\",\"PlaceBirth\":\"\",\"Dob\":\"07/17/1923\",\"Year\":null,\"MoreDob\":false,\"PrisonerNumber\":\"\",\"AUCode\":null,\"DescId\":\"581230\",\"Counter\":11,\"TreePath\":null,\"Signature\":\"2.1.1.1 - Information on foreigners from medical and health authorities of the district Hersfeld\",\"Father\":\"\",\"Mother\":\"\",\"Religion\":\"\",\"Nationality\":\"\",\"Occupaton\":\"\",\"Place_of_incarceration\":\"\",\"Date_of_decease\":\"\",\"Last_residence\":\"\",\"Last_residence_country\":\"\",\"Last_residence_district\":\"\",\"Last_residence_province\":\"\",\"Last_residence_town\":\"\",\"Last_residence_part_of_town\":\"\",\"Last_residence_street\":\"\",\"Last_residence_house_number\":\"\"},{\"__type\":\"ITSPannel.classes.PersData\",\"ObjId\":71187298,\"LastName\":\"BOWER\",\"FirstName\":\"Harry Georg\",\"MaidenName\":\"\",\"PlaceBirth\":\"\",\"Dob\":\"10/10/1922\",\"Year\":null,\"MoreDob\":false,\"PrisonerNumber\":\"\",\"AUCode\":null,\"DescId\":\"2714447\",\"Counter\":12,\"TreePath\":null,\"Signature\":\"2.1.7.5 - Lists of forced laborers and civilians interned by German administration in various other countries\",\"Father\":\"\",\"Mother\":\"\",\"Religion\":\"\",\"Nationality\":\"\",\"Occupaton\":\"\",\"Place_of_incarceration\":\"\",\"Date_of_decease\":\"\",\"Last_residence\":\"\",\"Last_residence_country\":\"\",\"Last_residence_district\":\"\",\"Last_residence_province\":\"\",\"Last_residence_town\":\"\",\"Last_residence_part_of_town\":\"\",\"Last_residence_street\":\"\",\"Last_residence_house_number\":\"\"},{\"__type\":\"ITSPannel.classes.PersData\",\"ObjId\":12100413,\"LastName\":\"BOYER\",\"FirstName\":\"HARRY\",\"MaidenName\":\"\",\"PlaceBirth\":\"\",\"Dob\":\"12/22/1914\",\"Year\":null,\"MoreDob\":false,\"PrisonerNumber\":\"\",\"AUCode\":null,\"DescId\":\"5429969\",\"Counter\":13,\"TreePath\":null,\"Signature\":\"1.2.2.1 - Compilations of names pertaining to documents received by and sent by the headquarters of the criminal investigations police in Berlin\",\"Father\":\"\",\"Mother\":\"\",\"Religion\":\"\",\"Nationality\":\"\",\"Occupaton\":\"\",\"Place_of_incarceration\":\"\",\"Date_of_decease\":\"\",\"Last_residence\":\"\",\"Last_residence_country\":\"\",\"Last_residence_district\":\"\",\"Last_residence_province\":\"\",\"Last_residence_town\":\"\",\"Last_residence_part_of_town\":\"\",\"Last_residence_street\":\"\",\"Last_residence_house_number\":\"\"},{\"__type\":\"ITSPannel.classes.PersData\",\"ObjId\":70397576,\"LastName\":\"BOYER\",\"FirstName\":\"Harry\",\"MaidenName\":\"\",\"PlaceBirth\":\"\",\"Dob\":\"\",\"Year\":null,\"MoreDob\":false,\"PrisonerNumber\":\"\",\"AUCode\":null,\"DescId\":\"580332\",\"Counter\":14,\"TreePath\":null,\"Signature\":\"2.1.1.1 - Information on foreigners being permanantly or temporarily present in the district Hanau during the war\",\"Father\":\"\",\"Mother\":\"\",\"Religion\":\"\",\"Nationality\":\"\",\"Occupaton\":\"\",\"Place_of_incarceration\":\"\",\"Date_of_decease\":\"\",\"Last_residence\":\"\",\"Last_residence_country\":\"\",\"Last_residence_district\":\"\",\"Last_residence_province\":\"\",\"Last_residence_town\":\"\",\"Last_residence_part_of_town\":\"\",\"Last_residence_street\":\"\",\"Last_residence_house_number\":\"\"},{\"__type\":\"ITSPannel.classes.PersData\",\"ObjId\":81689853,\"LastName\":\"BOYER\",\"FirstName\":\"Harry\",\"MaidenName\":\"\",\"PlaceBirth\":\"\",\"Dob\":\"02/01/1930\",\"Year\":null,\"MoreDob\":false,\"PrisonerNumber\":\"\",\"AUCode\":null,\"DescId\":\"22766\",\"Counter\":15,\"TreePath\":null,\"Signature\":\"3.1.3.2 - Emigrations in 1952/1953\",\"Father\":\"\",\"Mother\":\"\",\"Religion\":\"\",\"Nationality\":\"\",\"Occupaton\":\"\",\"Place_of_incarceration\":\"\",\"Date_of_decease\":\"\",\"Last_residence\":\"\",\"Last_residence_country\":\"\",\"Last_residence_district\":\"\",\"Last_residence_province\":\"\",\"Last_residence_town\":\"\",\"Last_residence_part_of_town\":\"\",\"Last_residence_street\":\"\",\"Last_residence_house_number\":\"\"}]}"
    },
    {
      "url": "https://collections-server.arolsen-archives.org/ITS-WS.asmx/GetCount",
      "status": 200,
      "requestPostData": "{\"uniqueId\":\"UmsdbMY4GsItJ7x1JzbE\",\"lang\":\"en\",\"searchType\":\"archive\",\"useFilter\":false}",
      "body": "{\"d\":\"0\"}"
    },
    {
      "url": "https://collections-server.arolsen-archives.org/ITS-WS.asmx/BuildGridFilter",
      "status": 200,
      "requestPostData": "{\"uniqueId\":\"UmsdbMY4GsItJ7x1JzbE\",\"lang\":\"en\",\"type\":\"person\",\"filter\":{\"Operator\":\"and\",\"Field\":\"\",\"Filters\":[{\"Field\":\"LastName\",\"Operator\":\"contains\",\"Value\":\"Bower Harris\"}],\"Value\":\"\"}}",
      "body": "{\"d\":null}"
    },
    {
      "url": "https://collections-server.arolsen-archives.org/ITS-WS.asmx/GetPersonList",
      "status": 200,
      "requestPostData": "{\"uniqueId\":\"UmsdbMY4GsItJ7x1JzbE\",\"lang\":\"en\",\"rowNum\":0,\"orderBy\":\"LastName\",\"orderType\":\"asc\"}",
      "body": "{\"d\":[]}"
    },
    {
      "url": "https://collections-server.arolsen-archives.org/ITS-WS.asmx/GetCount",
      "status": 200,
      "requestPostData": "{\"uniqueId\":\"UmsdbMY4GsItJ7x1JzbE\",\"lang\":\"en\",\"searchType\":\"person\",\"useFilter\":true}",
      "body": "{\"d\":\"0\"}"
    }
  ]
}